Workbook

Sheet LEIA-ME
A1: KIT DE EXECUÇÃO — O CUSTO INVISÍVEL DO OLHO SECO
A4: Versão 2.9.21 · 2026-07-13
A6: • Este arquivo separa capacidade equivalente, orçamento e resultado financeiro.
A7: • Capacidade equivalente não é perda contábil nem caixa recuperável.
A8: • ROI só deve ser calculado com benefício incremental atribuível e custo efetivo no mesmo horizonte.
A9: • OSDI, DEQ-5, CVS-Q, WPAI e WLQ não se convertem diretamente em dinheiro.
A10: • Dados individuais de saúde ficam com a equipe de saúde; a gestão recebe agregados.
A11: • Adapte instrumentos, base legal e fluxos com saúde ocupacional, jurídico e DPO.
A12: • Antes da coleta, classifique o projeto: melhoria interna ou pesquisa com seres humanos; consulte CEP/CONEP quando aplicável.
A14: Fluxo recomendado
A16: 1. Linha de base | B16: 2. BOM cotado | C16: 3. Intervenção limitada | D16: 4. Quatro gates | E16: 5. Confirmar / ajustar / encerrar

Sheet BOM
A1: Bloco | B1: Unidade | C1: Natureza | D1: Frequência / período | E1: Quantidade | F1: Valor unitário | G1: Total em H | H1: Fonte / fornecedor | I1: Data-base | J1: Inclui / exclui
A2: Desenho do protocolo | B2: projeto / hora | G2: =IF(OR(E2="",F2=""),"",E2*F2)
A3: Triagem e análise agregada | B3: campanha / pessoa | G3: =IF(OR(E3="",F3=""),"",E3*F3)
A4: Comunicação e treinamento | B4: campanha / turma | G4: =IF(OR(E4="",F4=""),"",E4*F4)
A5: Ergonomia e ambiente | B5: posto / área / item | G5: =IF(OR(E5="",F5=""),"",E5*F5)
A6: Lembretes e nudges | B6: licença / integração / hora | G6: =IF(OR(E6="",F6=""),"",E6*F6)
A7: Avaliação clínica seletiva | B7: atendimento | G7: =IF(OR(E7="",F7=""),"",E7*F7)
A8: Tratamento coberto | B8: pessoa / item | G8: =IF(OR(E8="",F8=""),"",E8*F8)
A9: Analytics e reavaliação | B9: ciclo / relatório | G9: =IF(OR(E9="",F9=""),"",E9*F9)
A10: Horas internas | B10: hora | G10: =IF(OR(E10="",F10=""),"",E10*F10)
A11: Privacidade, jurídico e DPO | B11: hora / projeto | G11: =IF(OR(E11="",F11=""),"",E11*F11)
A12: Deslocamento, impostos e contingência | B12: item | G12: =IF(OR(E12="",F12=""),"",E12*F12)
E14: K_H — total no horizonte | G14: =IF(COUNT(G2:G12)=0,"",SUM(G2:G12))

Sheet CAPACIDADE_E_CAIXA
A1: Variável | B1: Valor | C1: Fonte / regra
A2: H — horizonte comum (meses) | B2: 3 | C2: mesmo período para capacidade, custo e benefício
A3: N — colaboradores expostos | B3: 100 | C3: RH
A4: C_trabalho — custo direto anual | B4: 180000 | C4: remuneração + encargos + benefícios
A5: P — prevalência sintomática | B5: 0.5 | C5: triagem interna
A6: L — perda percebida/assumida do cenário | B6: 0.02 | C6: premissa de sensibilidade; não perda atribuível demonstrada
A7: Capacidade equivalente em H | B7: =IF(OR(B2="",B2<=0,B3="",B4="",B5="",B6=""),"",B3*B4*(B2/12)*B5*B6) | C7: rateio linear; cenário, não caixa; prefira custo real do período
A8: K_implantação em H | B8: =IF(SUMIF('BOM'!C2:C12,"Implantação",'BOM'!G2:G12)=0,"",SUMIF('BOM'!C2:C12,"Implantação",'BOM'!G2:G12)) | C8: itens únicos classificados no BOM
A9: K_recorrente em H | B9: =IF(SUMIF('BOM'!C2:C12,"Recorrente",'BOM'!G2:G12)=0,"",SUMIF('BOM'!C2:C12,"Recorrente",'BOM'!G2:G12)) | C9: frequência × períodos dentro de H
A10: K_H — custo total do BOM no horizonte | B10: =IF('BOM'!G14=0,"",'BOM'!G14) | C10: implantação + recorrência; fontes e datas documentadas
A11: Limiar de cobertura da capacidade | B11: =IF(OR(B10="",B7="",B7<=0),"",B10/B7) | C11: N/A quando capacidade ≤ 0; razão de planejamento, não ROI
A12: B_caixa,H — benefício financeiro incremental atribuível | B12: =IF(SUMIFS('FLUXO_CAIXA'!D2:D26,'FLUXO_CAIXA'!A2:A26,"<="&B2)=0,"",SUMIFS('FLUXO_CAIXA'!D2:D26,'FLUXO_CAIXA'!A2:A26,"<="&B2)) | C12: somente meses ≤ H; método e comparação declarados
A13: Resultado financeiro incremental em H | B13: =IF(OR(B12="",B10=""),"",B12-B10) | C13: B_caixa,H − K_H
A14: ROI financeiro observado em H | B14: =IF(OR(B13="",B10="",B10<=0),"",B13/B10) | C14: calcular somente após observação
A15: Payback observado (meses) | B15: =IFERROR(INDEX('FLUXO_CAIXA'!A2:A26,MATCH("SIM",'FLUXO_CAIXA'!G2:G26,0)),"") | C15: primeiro mês ≤ H em que o fluxo acumulado chega a ≥ 0
A17: Atenção | B17: Valores pré-preenchidos são didáticos. Substitua H, N, C, P e L. Quando P ou L for zero, o limiar fica N/A — nunca 0%. ROI e payback permanecem em branco até custos e benefício incremental atribuível serem observados e reconciliados no mesmo horizonte.

Sheet FLUXO_CAIXA
A1: Mês | B1: Custo de implantação | C1: Custo recorrente | D1: Benefício incremental atribuível | E1: Fluxo líquido | F1: Fluxo acumulado | G1: Payback atingido
A2: 0 | E2: =IF(COUNTA(B2:D2)=0,"",D2-B2-C2) | F2: =IF(COUNTA($B$2:D2)=0,"",SUM($E$2:E2)) | G2: =IF(A2>'CAPACIDADE_E_CAIXA'!B2,"",IF(F2="","",IF(F2>=0,"SIM","")))
A3: 1 | E3: =IF(COUNTA(B3:D3)=0,"",D3-B3-C3) | F3: =IF(COUNTA($B$2:D3)=0,"",SUM($E$2:E3)) | G3: =IF(A3>'CAPACIDADE_E_CAIXA'!B2,"",IF(F3="","",IF(AND(F3>=0,OR(F2="",F2<0)),"SIM","")))
A4: 2 | E4: =IF(COUNTA(B4:D4)=0,"",D4-B4-C4) | F4: =IF(COUNTA($B$2:D4)=0,"",SUM($E$2:E4)) | G4: =IF(A4>'CAPACIDADE_E_CAIXA'!B2,"",IF(F4="","",IF(AND(F4>=0,OR(F3="",F3<0)),"SIM","")))
A5: 3 | E5: =IF(COUNTA(B5:D5)=0,"",D5-B5-C5) | F5: =IF(COUNTA($B$2:D5)=0,"",SUM($E$2:E5)) | G5: =IF(A5>'CAPACIDADE_E_CAIXA'!B2,"",IF(F5="","",IF(AND(F5>=0,OR(F4="",F4<0)),"SIM","")))
A6: 4 | E6: =IF(COUNTA(B6:D6)=0,"",D6-B6-C6) | F6: =IF(COUNTA($B$2:D6)=0,"",SUM($E$2:E6)) | G6: =IF(A6>'CAPACIDADE_E_CAIXA'!B2,"",IF(F6="","",IF(AND(F6>=0,OR(F5="",F5<0)),"SIM","")))
A7: 5 | E7: =IF(COUNTA(B7:D7)=0,"",D7-B7-C7) | F7: =IF(COUNTA($B$2:D7)=0,"",SUM($E$2:E7)) | G7: =IF(A7>'CAPACIDADE_E_CAIXA'!B2,"",IF(F7="","",IF(AND(F7>=0,OR(F6="",F6<0)),"SIM","")))
A8: 6 | E8: =IF(COUNTA(B8:D8)=0,"",D8-B8-C8) | F8: =IF(COUNTA($B$2:D8)=0,"",SUM($E$2:E8)) | G8: =IF(A8>'CAPACIDADE_E_CAIXA'!B2,"",IF(F8="","",IF(AND(F8>=0,OR(F7="",F7<0)),"SIM","")))
A9: 7 | E9: =IF(COUNTA(B9:D9)=0,"",D9-B9-C9) | F9: =IF(COUNTA($B$2:D9)=0,"",SUM($E$2:E9)) | G9: =IF(A9>'CAPACIDADE_E_CAIXA'!B2,"",IF(F9="","",IF(AND(F9>=0,OR(F8="",F8<0)),"SIM","")))
A10: 8 | E10: =IF(COUNTA(B10:D10)=0,"",D10-B10-C10) | F10: =IF(COUNTA($B$2:D10)=0,"",SUM($E$2:E10)) | G10: =IF(A10>'CAPACIDADE_E_CAIXA'!B2,"",IF(F10="","",IF(AND(F10>=0,OR(F9="",F9<0)),"SIM","")))
A11: 9 | E11: =IF(COUNTA(B11:D11)=0,"",D11-B11-C11) | F11: =IF(COUNTA($B$2:D11)=0,"",SUM($E$2:E11)) | G11: =IF(A11>'CAPACIDADE_E_CAIXA'!B2,"",IF(F11="","",IF(AND(F11>=0,OR(F10="",F10<0)),"SIM","")))
A12: 10 | E12: =IF(COUNTA(B12:D12)=0,"",D12-B12-C12) | F12: =IF(COUNTA($B$2:D12)=0,"",SUM($E$2:E12)) | G12: =IF(A12>'CAPACIDADE_E_CAIXA'!B2,"",IF(F12="","",IF(AND(F12>=0,OR(F11="",F11<0)),"SIM","")))
A13: 11 | E13: =IF(COUNTA(B13:D13)=0,"",D13-B13-C13) | F13: =IF(COUNTA($B$2:D13)=0,"",SUM($E$2:E13)) | G13: =IF(A13>'CAPACIDADE_E_CAIXA'!B2,"",IF(F13="","",IF(AND(F13>=0,OR(F12="",F12<0)),"SIM","")))
A14: 12 | E14: =IF(COUNTA(B14:D14)=0,"",D14-B14-C14) | F14: =IF(COUNTA($B$2:D14)=0,"",SUM($E$2:E14)) | G14: =IF(A14>'CAPACIDADE_E_CAIXA'!B2,"",IF(F14="","",IF(AND(F14>=0,OR(F13="",F13<0)),"SIM","")))
A15: 13 | E15: =IF(COUNTA(B15:D15)=0,"",D15-B15-C15) | F15: =IF(COUNTA($B$2:D15)=0,"",SUM($E$2:E15)) | G15: =IF(A15>'CAPACIDADE_E_CAIXA'!B2,"",IF(F15="","",IF(AND(F15>=0,OR(F14="",F14<0)),"SIM","")))
A16: 14 | E16: =IF(COUNTA(B16:D16)=0,"",D16-B16-C16) | F16: =IF(COUNTA($B$2:D16)=0,"",SUM($E$2:E16)) | G16: =IF(A16>'CAPACIDADE_E_CAIXA'!B2,"",IF(F16="","",IF(AND(F16>=0,OR(F15="",F15<0)),"SIM","")))
A17: 15 | E17: =IF(COUNTA(B17:D17)=0,"",D17-B17-C17) | F17: =IF(COUNTA($B$2:D17)=0,"",SUM($E$2:E17)) | G17: =IF(A17>'CAPACIDADE_E_CAIXA'!B2,"",IF(F17="","",IF(AND(F17>=0,OR(F16="",F16<0)),"SIM","")))
A18: 16 | E18: =IF(COUNTA(B18:D18)=0,"",D18-B18-C18) | F18: =IF(COUNTA($B$2:D18)=0,"",SUM($E$2:E18)) | G18: =IF(A18>'CAPACIDADE_E_CAIXA'!B2,"",IF(F18="","",IF(AND(F18>=0,OR(F17="",F17<0)),"SIM","")))
A19: 17 | E19: =IF(COUNTA(B19:D19)=0,"",D19-B19-C19) | F19: =IF(COUNTA($B$2:D19)=0,"",SUM($E$2:E19)) | G19: =IF(A19>'CAPACIDADE_E_CAIXA'!B2,"",IF(F19="","",IF(AND(F19>=0,OR(F18="",F18<0)),"SIM","")))
A20: 18 | E20: =IF(COUNTA(B20:D20)=0,"",D20-B20-C20) | F20: =IF(COUNTA($B$2:D20)=0,"",SUM($E$2:E20)) | G20: =IF(A20>'CAPACIDADE_E_CAIXA'!B2,"",IF(F20="","",IF(AND(F20>=0,OR(F19="",F19<0)),"SIM","")))
A21: 19 | E21: =IF(COUNTA(B21:D21)=0,"",D21-B21-C21) | F21: =IF(COUNTA($B$2:D21)=0,"",SUM($E$2:E21)) | G21: =IF(A21>'CAPACIDADE_E_CAIXA'!B2,"",IF(F21="","",IF(AND(F21>=0,OR(F20="",F20<0)),"SIM","")))
A22: 20 | E22: =IF(COUNTA(B22:D22)=0,"",D22-B22-C22) | F22: =IF(COUNTA($B$2:D22)=0,"",SUM($E$2:E22)) | G22: =IF(A22>'CAPACIDADE_E_CAIXA'!B2,"",IF(F22="","",IF(AND(F22>=0,OR(F21="",F21<0)),"SIM","")))
A23: 21 | E23: =IF(COUNTA(B23:D23)=0,"",D23-B23-C23) | F23: =IF(COUNTA($B$2:D23)=0,"",SUM($E$2:E23)) | G23: =IF(A23>'CAPACIDADE_E_CAIXA'!B2,"",IF(F23="","",IF(AND(F23>=0,OR(F22="",F22<0)),"SIM","")))
A24: 22 | E24: =IF(COUNTA(B24:D24)=0,"",D24-B24-C24) | F24: =IF(COUNTA($B$2:D24)=0,"",SUM($E$2:E24)) | G24: =IF(A24>'CAPACIDADE_E_CAIXA'!B2,"",IF(F24="","",IF(AND(F24>=0,OR(F23="",F23<0)),"SIM","")))
A25: 23 | E25: =IF(COUNTA(B25:D25)=0,"",D25-B25-C25) | F25: =IF(COUNTA($B$2:D25)=0,"",SUM($E$2:E25)) | G25: =IF(A25>'CAPACIDADE_E_CAIXA'!B2,"",IF(F25="","",IF(AND(F25>=0,OR(F24="",F24<0)),"SIM","")))
A26: 24 | E26: =IF(COUNTA(B26:D26)=0,"",D26-B26-C26) | F26: =IF(COUNTA($B$2:D26)=0,"",SUM($E$2:E26)) | G26: =IF(A26>'CAPACIDADE_E_CAIXA'!B2,"",IF(F26="","",IF(AND(F26>=0,OR(F25="",F25<0)),"SIM","")))
A27: A decisão em H usa somente meses ≤ H; meses posteriores são informativos e não entram no ROI nem no payback em H.
A28: Total de custos no fluxo em H | B28: =IF(COUNTIFS(A2:A26,"<="&'CAPACIDADE_E_CAIXA'!B2,B2:B26,"<>")+COUNTIFS(A2:A26,"<="&'CAPACIDADE_E_CAIXA'!B2,C2:C26,"<>")=0,"",SUMIFS(B2:B26,A2:A26,"<="&'CAPACIDADE_E_CAIXA'!B2)+SUMIFS(C2:C26,A2:A26,"<="&'CAPACIDADE_E_CAIXA'!B2))
A29: K_H no BOM | B29: ='CAPACIDADE_E_CAIXA'!B10
A30: Diferença a reconciliar | B30: =IF(OR(B28="",B29=""),"",B28-B29)
A31: Status | B31: =IF(B30="","PENDENTE",IF(ABS(B30)<0.01,"OK","RECONCILIAR"))
A33: Visão 0–24 meses — informativa, fora do ROI em H
A34: Custos de vida completa | B34: =IF(COUNTA(B2:C26)=0,"",SUM(B2:C26))
A35: Benefício de vida completa | B35: =IF(COUNT(D2:D26)=0,"",SUM(D2:D26))
A36: Resultado de vida completa | B36: =IF(OR(B34="",B35=""),"",B35-B34)

Sheet QUATRO_GATES
A1: Gate | B1: Pergunta | C1: Indicadores pré-especificados | D1: Evidência | E1: Status | F1: Decisão
A2: Implementação | B2: A intervenção chegou como planejado? | C2: alcance; adesão; perdas; fidelidade; eventos | E2: Pendente
A3: Clínico | B3: Sintomas mudaram com relevância e incerteza aceitáveis? | C3: instrumento; efeito; IC; segurança | E3: Pendente
A4: Operacional | B4: Há sinal em indicador objetivo independente? | C4: um indicador definido antes; comparação proporcional | E4: Exploratório
A5: Financeiro | B5: Existe benefício incremental auditável e atribuível? | C5: B_caixa,H; K_H; método; mesmo horizonte | E5: Fechado

Sheet PROTOCOLO_E_LIBERACOES
A1: Contrato mínimo antes da coleta | B1: Registro | C1: Status / evidência
A2: Finalidade: melhoria interna ou pesquisa; decisão CEP/CONEP quando aplicável | C2: Pendente
A3: População, equipes/períodos e unidade de análise | C3: Pendente
A4: Desfecho principal de viabilidade e desfechos separados | C4: Pendente
A5: Comparação, horizonte, perdas/dados ausentes e incerteza a relatar | C5: Pendente
A6: Critérios prévios: confirmar melhor / ajustar / encerrar | C6: Pendente
A7: OSDI/OSDI-6: versão, idioma, licença, algoritmo e evidência | C7: Pendente
A8: DEQ-5: versão PT-BR, condições de uso e corte correspondente | C8: Pendente
A9: CVS-Q: versão autorizada, população e corte correspondente | C9: Pendente
A10: WPAI/WLQ, se usados: domínio, tradução, licença e finalidade | C10: Pendente

Sheet RELATORIO_D90
A1: Indicador | B1: Piloto baseline | C1: Piloto D+90 | D1: Comparação baseline | E1: Comparação D+90 | F1: Efeito / IC | G1: Observação
A2: Participação / alcance
A3: Perdas de acompanhamento
A4: Adesão a pausas / ergonomia
A5: Fadiga de notificação
A6: Escore de sintomas
A7: % nas faixas moderada/grave do OSDI-12, se aplicável
A8: Produtividade percebida
A9: Indicador operacional pré-especificado
A10: Eventos de segurança
A11: K_H — custo no mesmo horizonte
A12: B_caixa,H incremental atribuível

Sheet CHECAGENS
A1: Controle | B1: Status | C1: Onde corrigir | D1: Regra
A2: Horizonte comum definido | B2: =IF('CAPACIDADE_E_CAIXA'!B2>0,"OK","FALHA") | C2: CAPACIDADE_E_CAIXA!B2 | D2: H deve ser maior que zero
A3: Premissas P e L em faixa válida | B3: =IF(AND('CAPACIDADE_E_CAIXA'!B5>=0,'CAPACIDADE_E_CAIXA'!B5<=1,'CAPACIDADE_E_CAIXA'!B6>=0,'CAPACIDADE_E_CAIXA'!B6<=1),"OK","FALHA") | C3: CAPACIDADE_E_CAIXA!B5:B6 | D3: percentuais entre 0% e 100%
A4: Custos do BOM classificados | B4: =IF(COUNT('BOM'!G2:G12)=0,"PENDENTE",IF(COUNTIFS('BOM'!G2:G12,">0",'BOM'!C2:C12,"")=0,"OK","FALHA")) | C4: BOM!C2:C12 | D4: todo custo deve ser implantação ou recorrente
A5: Fluxo de custos reconcilia com K_H | B5: ='FLUXO_CAIXA'!B31 | C5: FLUXO_CAIXA!B2:C26 | D5: diferença menor que R$ 0,01
A6: Denominador zero tratado como N/A | B6: =IF('CAPACIDADE_E_CAIXA'!B7<=0,IF('CAPACIDADE_E_CAIXA'!B11="","OK","FALHA"),"OK") | C6: CAPACIDADE_E_CAIXA!B11 | D6: limiar nunca deve mostrar 0% por divisão inválida
A7: ROI bloqueado sem custo e benefício | B7: =IF(OR('CAPACIDADE_E_CAIXA'!B10="",'CAPACIDADE_E_CAIXA'!B12=""),IF('CAPACIDADE_E_CAIXA'!B14="","OK","FALHA"),"OK") | C7: CAPACIDADE_E_CAIXA!B14 | D7: sem inputs observados, ROI fica em branco
A8: Benefício financeiro limitado a H | B8: =IF(ABS(N('CAPACIDADE_E_CAIXA'!B12)-SUMIFS('FLUXO_CAIXA'!D2:D26,'FLUXO_CAIXA'!A2:A26,"<="&'CAPACIDADE_E_CAIXA'!B2))<0.01,"OK","FALHA") | C8: CAPACIDADE_E_CAIXA!B12 | D8: B_caixa,H não inclui meses posteriores a H
A9: Payback limitado a H | B9: =IF(OR('CAPACIDADE_E_CAIXA'!B15="",AND('CAPACIDADE_E_CAIXA'!B15>=0,'CAPACIDADE_E_CAIXA'!B15<='CAPACIDADE_E_CAIXA'!B2)),"OK","FALHA") | C9: CAPACIDADE_E_CAIXA!B15 | D9: payback posterior a H permanece fora do ROI em H
A11: MODEL STATUS | B11: =IF(COUNTIF(B2:B9,"FALHA")+COUNTIF(B2:B9,"RECONCILIAR")>0,"FAIL",IF(COUNTIF(B2:B9,"PENDENTE")>0,"PENDENTE","PASS"))
